<?xml version="1.0" encoding="UTF-8"?>
<annotations textSource="12546709.txt">
  <annotation>
    <mention id="GO_CC_2016_02_16_Instance_101571" />
    <span start="1157" end="1164" />
    <spannedText>nucleic</spannedText>
  </annotation>
  <annotation>
    <mention id="GO_CC_2016_02_16_Instance_101573" />
    <span start="9132" end="9139" />
    <spannedText>nucleic</spannedText>
  </annotation>
  <annotation>
    <mention id="GO_CC_2016_02_16_Instance_101575" />
    <span start="12942" end="12949" />
    <spannedText>nucleic</spannedText>
  </annotation>
  <annotation>
    <mention id="GO_CC_2016_02_16_Instance_101577" />
    <span start="13461" end="13468" />
    <spannedText>nucleic</spannedText>
  </annotation>
  <annotation>
    <mention id="GO_CC_2016_02_16_Instance_101579" />
    <span start="13576" end="13583" />
    <spannedText>nucleic</spannedText>
  </annotation>
  <annotation>
    <mention id="GO_CC_2016_02_16_Instance_101581" />
    <span start="14315" end="14322" />
    <spannedText>nucleic</spannedText>
  </annotation>
  <annotation>
    <mention id="GO_CC_2016_02_16_Instance_101583" />
    <span start="17088" end="17095" />
    <spannedText>nucleic</spannedText>
  </annotation>
  <annotation>
    <mention id="GO_CC_2016_02_16_Instance_101585" />
    <span start="17507" end="17514" />
    <spannedText>nucleic</spannedText>
  </annotation>
  <annotation>
    <mention id="GO_CC_2016_02_16_Instance_101587" />
    <span start="19111" end="19118" />
    <spannedText>nucleic</spannedText>
  </annotation>
  <annotation>
    <mention id="GO_CC_2016_02_16_Instance_101589" />
    <span start="23622" end="23629" />
    <spannedText>nucleic</spannedText>
  </annotation>
  <annotation>
    <mention id="GO_CC_2016_02_16_Instance_101591" />
    <span start="26805" end="26812" />
    <spannedText>nucleic</spannedText>
  </annotation>
  <annotation>
    <mention id="GO_CC_2016_02_16_Instance_101593" />
    <span start="27118" end="27125" />
    <spannedText>nucleic</spannedText>
  </annotation>
  <annotation>
    <mention id="GO_CC_2016_02_16_Instance_101595" />
    <span start="27208" end="27215" />
    <spannedText>nucleic</spannedText>
  </annotation>
  <annotation>
    <mention id="GO_CC_2016_02_16_Instance_101597" />
    <span start="27651" end="27658" />
    <spannedText>nucleic</spannedText>
  </annotation>
  <annotation>
    <mention id="GO_CC_2016_02_16_Instance_101599" />
    <span start="27839" end="27846" />
    <spannedText>nucleic</spannedText>
  </annotation>
  <annotation>
    <mention id="GO_CC_2016_02_16_Instance_101601" />
    <span start="31847" end="31854" />
    <spannedText>nucleic</spannedText>
  </annotation>
  <annotation>
    <mention id="GO_CC_2016_02_16_Instance_101679" />
    <span start="13329" end="13334" />
    <spannedText>cells</spannedText>
  </annotation>
  <annotation>
    <mention id="GO_CC_2016_02_16_Instance_102535" />
    <span start="19187" end="19198" />
    <spannedText>projections</spannedText>
  </annotation>
  <annotation>
    <mention id="GO_CC_2016_02_16_Instance_102537" />
    <span start="20533" end="20544" />
    <spannedText>projections</spannedText>
  </annotation>
  <annotation>
    <mention id="GO_CC_2016_02_16_Instance_102539" />
    <span start="21186" end="21197" />
    <spannedText>projections</spannedText>
  </annotation>
  <annotation>
    <mention id="GO_CC_2016_02_16_Instance_102541" />
    <span start="21285" end="21296" />
    <spannedText>projections</spannedText>
  </annotation>
  <annotation>
    <mention id="GO_CC_2016_02_16_Instance_133" />
    <span start="19178" end="19186" />
    <spannedText>membrane</spannedText>
  </annotation>
  <annotation>
    <mention id="GO_CC_2016_02_16_Instance_143" />
    <span start="32487" end="32494" />
    <spannedText>complex</spannedText>
  </annotation>
  <annotation>
    <mention id="GO_CC_2016_02_16_Instance_145" />
    <span start="33073" end="33079" />
    <spannedText>cellar</spannedText>
  </annotation>
  <annotation>
    <mention id="GO_CC_2016_02_16_Instance_190003" />
    <span start="13300" end="13320" />
    <spannedText>extracellular spaces</spannedText>
  </annotation>
  <annotation>
    <mention id="GO_CC_2016_02_16_test_Instance_10091" />
    <annotator id="GO_CC_2016_02_16_test_Instance_10000">Mike Bada, University of Colorado Anschutz Medical Campus</annotator>
    <span start="19023" end="19028" />
    <spannedText>Cells</spannedText>
  </annotation>
  <annotation>
    <mention id="GO_CC_2016_02_16_test_Instance_10587" />
    <annotator id="GO_CC_2016_02_16_test_Instance_10000">Mike Bada, University of Colorado Anschutz Medical Campus</annotator>
    <span start="1061" end="1066" />
    <spannedText>cells</spannedText>
  </annotation>
  <annotation>
    <mention id="GO_CC_2016_02_16_test_Instance_10589" />
    <annotator id="GO_CC_2016_02_16_test_Instance_10000">Mike Bada, University of Colorado Anschutz Medical Campus</annotator>
    <span start="1878" end="1883" />
    <spannedText>cells</spannedText>
  </annotation>
  <annotation>
    <mention id="GO_CC_2016_02_16_test_Instance_10591" />
    <annotator id="GO_CC_2016_02_16_test_Instance_10000">Mike Bada, University of Colorado Anschutz Medical Campus</annotator>
    <span start="2263" end="2268" />
    <spannedText>cells</spannedText>
  </annotation>
  <annotation>
    <mention id="GO_CC_2016_02_16_test_Instance_10593" />
    <annotator id="GO_CC_2016_02_16_test_Instance_10000">Mike Bada, University of Colorado Anschutz Medical Campus</annotator>
    <span start="2294" end="2299" />
    <spannedText>cells</spannedText>
  </annotation>
  <annotation>
    <mention id="GO_CC_2016_02_16_test_Instance_10595" />
    <annotator id="GO_CC_2016_02_16_test_Instance_10000">Mike Bada, University of Colorado Anschutz Medical Campus</annotator>
    <span start="2536" end="2541" />
    <spannedText>cells</spannedText>
  </annotation>
  <annotation>
    <mention id="GO_CC_2016_02_16_test_Instance_10597" />
    <annotator id="GO_CC_2016_02_16_test_Instance_10000">Mike Bada, University of Colorado Anschutz Medical Campus</annotator>
    <span start="2795" end="2803" />
    <spannedText>cellular</spannedText>
  </annotation>
  <annotation>
    <mention id="GO_CC_2016_02_16_test_Instance_10599" />
    <annotator id="GO_CC_2016_02_16_test_Instance_10000">Mike Bada, University of Colorado Anschutz Medical Campus</annotator>
    <span start="3881" end="3889" />
    <spannedText>cellular</spannedText>
  </annotation>
  <annotation>
    <mention id="GO_CC_2016_02_16_test_Instance_10601" />
    <annotator id="GO_CC_2016_02_16_test_Instance_10000">Mike Bada, University of Colorado Anschutz Medical Campus</annotator>
    <span start="4159" end="4164" />
    <spannedText>cells</spannedText>
  </annotation>
  <annotation>
    <mention id="GO_CC_2016_02_16_test_Instance_10603" />
    <annotator id="GO_CC_2016_02_16_test_Instance_10000">Mike Bada, University of Colorado Anschutz Medical Campus</annotator>
    <span start="4766" end="4771" />
    <spannedText>cells</spannedText>
  </annotation>
  <annotation>
    <mention id="GO_CC_2016_02_16_test_Instance_10605" />
    <annotator id="GO_CC_2016_02_16_test_Instance_10000">Mike Bada, University of Colorado Anschutz Medical Campus</annotator>
    <span start="5003" end="5008" />
    <spannedText>cells</spannedText>
  </annotation>
  <annotation>
    <mention id="GO_CC_2016_02_16_test_Instance_10607" />
    <annotator id="GO_CC_2016_02_16_test_Instance_10000">Mike Bada, University of Colorado Anschutz Medical Campus</annotator>
    <span start="5201" end="5205" />
    <spannedText>cell</spannedText>
  </annotation>
  <annotation>
    <mention id="GO_CC_2016_02_16_test_Instance_10609" />
    <annotator id="GO_CC_2016_02_16_test_Instance_10000">Mike Bada, University of Colorado Anschutz Medical Campus</annotator>
    <span start="6111" end="6116" />
    <spannedText>cells</spannedText>
  </annotation>
  <annotation>
    <mention id="GO_CC_2016_02_16_test_Instance_10611" />
    <annotator id="GO_CC_2016_02_16_test_Instance_10000">Mike Bada, University of Colorado Anschutz Medical Campus</annotator>
    <span start="6332" end="6336" />
    <spannedText>cell</spannedText>
  </annotation>
  <annotation>
    <mention id="GO_CC_2016_02_16_test_Instance_10613" />
    <annotator id="GO_CC_2016_02_16_test_Instance_10000">Mike Bada, University of Colorado Anschutz Medical Campus</annotator>
    <span start="7158" end="7162" />
    <spannedText>cell</spannedText>
  </annotation>
  <annotation>
    <mention id="GO_CC_2016_02_16_test_Instance_10617" />
    <annotator id="GO_CC_2016_02_16_test_Instance_10000">Mike Bada, University of Colorado Anschutz Medical Campus</annotator>
    <span start="13746" end="13751" />
    <spannedText>cells</spannedText>
  </annotation>
  <annotation>
    <mention id="GO_CC_2016_02_16_test_Instance_10619" />
    <annotator id="GO_CC_2016_02_16_test_Instance_10000">Mike Bada, University of Colorado Anschutz Medical Campus</annotator>
    <span start="13828" end="13836" />
    <spannedText>cellular</spannedText>
  </annotation>
  <annotation>
    <mention id="GO_CC_2016_02_16_test_Instance_10621" />
    <annotator id="GO_CC_2016_02_16_test_Instance_10000">Mike Bada, University of Colorado Anschutz Medical Campus</annotator>
    <span start="15737" end="15745" />
    <spannedText>cellular</spannedText>
  </annotation>
  <annotation>
    <mention id="GO_CC_2016_02_16_test_Instance_10623" />
    <annotator id="GO_CC_2016_02_16_test_Instance_10000">Mike Bada, University of Colorado Anschutz Medical Campus</annotator>
    <span start="16919" end="16924" />
    <spannedText>cells</spannedText>
  </annotation>
  <annotation>
    <mention id="GO_CC_2016_02_16_test_Instance_10625" />
    <annotator id="GO_CC_2016_02_16_test_Instance_10000">Mike Bada, University of Colorado Anschutz Medical Campus</annotator>
    <span start="17182" end="17187" />
    <spannedText>cells</spannedText>
  </annotation>
  <annotation>
    <mention id="GO_CC_2016_02_16_test_Instance_10627" />
    <annotator id="GO_CC_2016_02_16_test_Instance_10000">Mike Bada, University of Colorado Anschutz Medical Campus</annotator>
    <span start="17458" end="17466" />
    <spannedText>cellular</spannedText>
  </annotation>
  <annotation>
    <mention id="GO_CC_2016_02_16_test_Instance_10629" />
    <annotator id="GO_CC_2016_02_16_test_Instance_10000">Mike Bada, University of Colorado Anschutz Medical Campus</annotator>
    <span start="17582" end="17587" />
    <spannedText>cells</spannedText>
  </annotation>
  <annotation>
    <mention id="GO_CC_2016_02_16_test_Instance_10631" />
    <annotator id="GO_CC_2016_02_16_test_Instance_10000">Mike Bada, University of Colorado Anschutz Medical Campus</annotator>
    <span start="17698" end="17703" />
    <spannedText>cells</spannedText>
  </annotation>
  <annotation>
    <mention id="GO_CC_2016_02_16_test_Instance_10633" />
    <annotator id="GO_CC_2016_02_16_test_Instance_10000">Mike Bada, University of Colorado Anschutz Medical Campus</annotator>
    <span start="18060" end="18068" />
    <spannedText>cellular</spannedText>
  </annotation>
  <annotation>
    <mention id="GO_CC_2016_02_16_test_Instance_10635" />
    <annotator id="GO_CC_2016_02_16_test_Instance_10000">Mike Bada, University of Colorado Anschutz Medical Campus</annotator>
    <span start="18197" end="18202" />
    <spannedText>cells</spannedText>
  </annotation>
  <annotation>
    <mention id="GO_CC_2016_02_16_test_Instance_10637" />
    <annotator id="GO_CC_2016_02_16_test_Instance_10000">Mike Bada, University of Colorado Anschutz Medical Campus</annotator>
    <span start="18460" end="18465" />
    <spannedText>cells</spannedText>
  </annotation>
  <annotation>
    <mention id="GO_CC_2016_02_16_test_Instance_10639" />
    <annotator id="GO_CC_2016_02_16_test_Instance_10000">Mike Bada, University of Colorado Anschutz Medical Campus</annotator>
    <span start="18608" end="18612" />
    <spannedText>cell</spannedText>
  </annotation>
  <annotation>
    <mention id="GO_CC_2016_02_16_test_Instance_10641" />
    <annotator id="GO_CC_2016_02_16_test_Instance_10000">Mike Bada, University of Colorado Anschutz Medical Campus</annotator>
    <span start="18852" end="18857" />
    <spannedText>cells</spannedText>
  </annotation>
  <annotation>
    <mention id="GO_CC_2016_02_16_test_Instance_10643" />
    <annotator id="GO_CC_2016_02_16_test_Instance_10000">Mike Bada, University of Colorado Anschutz Medical Campus</annotator>
    <span start="19010" end="19014" />
    <spannedText>cell</spannedText>
  </annotation>
  <annotation>
    <mention id="GO_CC_2016_02_16_test_Instance_10645" />
    <annotator id="GO_CC_2016_02_16_test_Instance_10000">Mike Bada, University of Colorado Anschutz Medical Campus</annotator>
    <span start="19337" end="19342" />
    <spannedText>cells</spannedText>
  </annotation>
  <annotation>
    <mention id="GO_CC_2016_02_16_test_Instance_10647" />
    <annotator id="GO_CC_2016_02_16_test_Instance_10000">Mike Bada, University of Colorado Anschutz Medical Campus</annotator>
    <span start="19439" end="19444" />
    <spannedText>cells</spannedText>
  </annotation>
  <annotation>
    <mention id="GO_CC_2016_02_16_test_Instance_10649" />
    <annotator id="GO_CC_2016_02_16_test_Instance_10000">Mike Bada, University of Colorado Anschutz Medical Campus</annotator>
    <span start="19826" end="19831" />
    <spannedText>cells</spannedText>
  </annotation>
  <annotation>
    <mention id="GO_CC_2016_02_16_test_Instance_10651" />
    <annotator id="GO_CC_2016_02_16_test_Instance_10000">Mike Bada, University of Colorado Anschutz Medical Campus</annotator>
    <span start="20146" end="20151" />
    <spannedText>cells</spannedText>
  </annotation>
  <annotation>
    <mention id="GO_CC_2016_02_16_test_Instance_10653" />
    <annotator id="GO_CC_2016_02_16_test_Instance_10000">Mike Bada, University of Colorado Anschutz Medical Campus</annotator>
    <span start="20249" end="20254" />
    <spannedText>cells</spannedText>
  </annotation>
  <annotation>
    <mention id="GO_CC_2016_02_16_test_Instance_10655" />
    <annotator id="GO_CC_2016_02_16_test_Instance_10000">Mike Bada, University of Colorado Anschutz Medical Campus</annotator>
    <span start="20500" end="20505" />
    <spannedText>cells</spannedText>
  </annotation>
  <annotation>
    <mention id="GO_CC_2016_02_16_test_Instance_10659" />
    <annotator id="GO_CC_2016_02_16_test_Instance_10000">Mike Bada, University of Colorado Anschutz Medical Campus</annotator>
    <span start="20706" end="20711" />
    <spannedText>cells</spannedText>
  </annotation>
  <annotation>
    <mention id="GO_CC_2016_02_16_test_Instance_10661" />
    <annotator id="GO_CC_2016_02_16_test_Instance_10000">Mike Bada, University of Colorado Anschutz Medical Campus</annotator>
    <span start="20820" end="20825" />
    <spannedText>cells</spannedText>
  </annotation>
  <annotation>
    <mention id="GO_CC_2016_02_16_test_Instance_10663" />
    <annotator id="GO_CC_2016_02_16_test_Instance_10000">Mike Bada, University of Colorado Anschutz Medical Campus</annotator>
    <span start="21153" end="21158" />
    <spannedText>cells</spannedText>
  </annotation>
  <annotation>
    <mention id="GO_CC_2016_02_16_test_Instance_10667" />
    <annotator id="GO_CC_2016_02_16_test_Instance_10000">Mike Bada, University of Colorado Anschutz Medical Campus</annotator>
    <span start="21247" end="21252" />
    <spannedText>cells</spannedText>
  </annotation>
  <annotation>
    <mention id="GO_CC_2016_02_16_test_Instance_10669" />
    <annotator id="GO_CC_2016_02_16_test_Instance_10000">Mike Bada, University of Colorado Anschutz Medical Campus</annotator>
    <span start="21359" end="21364" />
    <spannedText>cells</spannedText>
  </annotation>
  <annotation>
    <mention id="GO_CC_2016_02_16_test_Instance_10671" />
    <annotator id="GO_CC_2016_02_16_test_Instance_10000">Mike Bada, University of Colorado Anschutz Medical Campus</annotator>
    <span start="21503" end="21508" />
    <spannedText>cells</spannedText>
  </annotation>
  <annotation>
    <mention id="GO_CC_2016_02_16_test_Instance_10673" />
    <annotator id="GO_CC_2016_02_16_test_Instance_10000">Mike Bada, University of Colorado Anschutz Medical Campus</annotator>
    <span start="21723" end="21728" />
    <spannedText>cells</spannedText>
  </annotation>
  <annotation>
    <mention id="GO_CC_2016_02_16_test_Instance_10675" />
    <annotator id="GO_CC_2016_02_16_test_Instance_10000">Mike Bada, University of Colorado Anschutz Medical Campus</annotator>
    <span start="23547" end="23552" />
    <spannedText>cells</spannedText>
  </annotation>
  <annotation>
    <mention id="GO_CC_2016_02_16_test_Instance_10677" />
    <annotator id="GO_CC_2016_02_16_test_Instance_10000">Mike Bada, University of Colorado Anschutz Medical Campus</annotator>
    <span start="24389" end="24394" />
    <spannedText>cells</spannedText>
  </annotation>
  <annotation>
    <mention id="GO_CC_2016_02_16_test_Instance_10679" />
    <annotator id="GO_CC_2016_02_16_test_Instance_10000">Mike Bada, University of Colorado Anschutz Medical Campus</annotator>
    <span start="24433" end="24438" />
    <spannedText>cells</spannedText>
  </annotation>
  <annotation>
    <mention id="GO_CC_2016_02_16_test_Instance_10681" />
    <annotator id="GO_CC_2016_02_16_test_Instance_10000">Mike Bada, University of Colorado Anschutz Medical Campus</annotator>
    <span start="24499" end="24503" />
    <spannedText>cell</spannedText>
  </annotation>
  <annotation>
    <mention id="GO_CC_2016_02_16_test_Instance_10683" />
    <annotator id="GO_CC_2016_02_16_test_Instance_10000">Mike Bada, University of Colorado Anschutz Medical Campus</annotator>
    <span start="24609" end="24614" />
    <spannedText>cells</spannedText>
  </annotation>
  <annotation>
    <mention id="GO_CC_2016_02_16_test_Instance_10685" />
    <annotator id="GO_CC_2016_02_16_test_Instance_10000">Mike Bada, University of Colorado Anschutz Medical Campus</annotator>
    <span start="24679" end="24684" />
    <spannedText>cells</spannedText>
  </annotation>
  <annotation>
    <mention id="GO_CC_2016_02_16_test_Instance_10687" />
    <annotator id="GO_CC_2016_02_16_test_Instance_10000">Mike Bada, University of Colorado Anschutz Medical Campus</annotator>
    <span start="24751" end="24756" />
    <spannedText>cells</spannedText>
  </annotation>
  <annotation>
    <mention id="GO_CC_2016_02_16_test_Instance_10689" />
    <annotator id="GO_CC_2016_02_16_test_Instance_10000">Mike Bada, University of Colorado Anschutz Medical Campus</annotator>
    <span start="24804" end="24809" />
    <spannedText>cells</spannedText>
  </annotation>
  <annotation>
    <mention id="GO_CC_2016_02_16_test_Instance_10691" />
    <annotator id="GO_CC_2016_02_16_test_Instance_10000">Mike Bada, University of Colorado Anschutz Medical Campus</annotator>
    <span start="24821" end="24829" />
    <spannedText>cellular</spannedText>
  </annotation>
  <annotation>
    <mention id="GO_CC_2016_02_16_test_Instance_10693" />
    <annotator id="GO_CC_2016_02_16_test_Instance_10000">Mike Bada, University of Colorado Anschutz Medical Campus</annotator>
    <span start="24867" end="24872" />
    <spannedText>cells</spannedText>
  </annotation>
  <annotation>
    <mention id="GO_CC_2016_02_16_test_Instance_10695" />
    <annotator id="GO_CC_2016_02_16_test_Instance_10000">Mike Bada, University of Colorado Anschutz Medical Campus</annotator>
    <span start="25108" end="25113" />
    <spannedText>cells</spannedText>
  </annotation>
  <annotation>
    <mention id="GO_CC_2016_02_16_test_Instance_10697" />
    <annotator id="GO_CC_2016_02_16_test_Instance_10000">Mike Bada, University of Colorado Anschutz Medical Campus</annotator>
    <span start="25279" end="25284" />
    <spannedText>cells</spannedText>
  </annotation>
  <annotation>
    <mention id="GO_CC_2016_02_16_test_Instance_10705" />
    <annotator id="GO_CC_2016_02_16_test_Instance_10000">Mike Bada, University of Colorado Anschutz Medical Campus</annotator>
    <span start="25750" end="25755" />
    <spannedText>cells</spannedText>
  </annotation>
  <annotation>
    <mention id="GO_CC_2016_02_16_test_Instance_10707" />
    <annotator id="GO_CC_2016_02_16_test_Instance_10000">Mike Bada, University of Colorado Anschutz Medical Campus</annotator>
    <span start="25767" end="25772" />
    <spannedText>cells</spannedText>
  </annotation>
  <annotation>
    <mention id="GO_CC_2016_02_16_test_Instance_10709" />
    <annotator id="GO_CC_2016_02_16_test_Instance_10000">Mike Bada, University of Colorado Anschutz Medical Campus</annotator>
    <span start="26887" end="26892" />
    <spannedText>cells</spannedText>
  </annotation>
  <annotation>
    <mention id="GO_CC_2016_02_16_test_Instance_10711" />
    <annotator id="GO_CC_2016_02_16_test_Instance_10000">Mike Bada, University of Colorado Anschutz Medical Campus</annotator>
    <span start="27312" end="27317" />
    <spannedText>cells</spannedText>
  </annotation>
  <annotation>
    <mention id="GO_CC_2016_02_16_test_Instance_10713" />
    <annotator id="GO_CC_2016_02_16_test_Instance_10000">Mike Bada, University of Colorado Anschutz Medical Campus</annotator>
    <span start="27379" end="27384" />
    <spannedText>cells</spannedText>
  </annotation>
  <annotation>
    <mention id="GO_CC_2016_02_16_test_Instance_10715" />
    <annotator id="GO_CC_2016_02_16_test_Instance_10000">Mike Bada, University of Colorado Anschutz Medical Campus</annotator>
    <span start="27863" end="27868" />
    <spannedText>cells</spannedText>
  </annotation>
  <annotation>
    <mention id="GO_CC_2016_02_16_test_Instance_10717" />
    <annotator id="GO_CC_2016_02_16_test_Instance_10000">Mike Bada, University of Colorado Anschutz Medical Campus</annotator>
    <span start="28361" end="28366" />
    <spannedText>cells</spannedText>
  </annotation>
  <annotation>
    <mention id="GO_CC_2016_02_16_test_Instance_10719" />
    <annotator id="GO_CC_2016_02_16_test_Instance_10000">Mike Bada, University of Colorado Anschutz Medical Campus</annotator>
    <span start="28511" end="28515" />
    <spannedText>cell</spannedText>
  </annotation>
  <annotation>
    <mention id="GO_CC_2016_02_16_test_Instance_10721" />
    <annotator id="GO_CC_2016_02_16_test_Instance_10000">Mike Bada, University of Colorado Anschutz Medical Campus</annotator>
    <span start="28564" end="28568" />
    <spannedText>cell</spannedText>
  </annotation>
  <annotation>
    <mention id="GO_CC_2016_02_16_test_Instance_10723" />
    <annotator id="GO_CC_2016_02_16_test_Instance_10000">Mike Bada, University of Colorado Anschutz Medical Campus</annotator>
    <span start="28582" end="28586" />
    <spannedText>cell</spannedText>
  </annotation>
  <annotation>
    <mention id="GO_CC_2016_02_16_test_Instance_10725" />
    <annotator id="GO_CC_2016_02_16_test_Instance_10000">Mike Bada, University of Colorado Anschutz Medical Campus</annotator>
    <span start="28667" end="28671" />
    <spannedText>cell</spannedText>
  </annotation>
  <annotation>
    <mention id="GO_CC_2016_02_16_test_Instance_10727" />
    <annotator id="GO_CC_2016_02_16_test_Instance_10000">Mike Bada, University of Colorado Anschutz Medical Campus</annotator>
    <span start="28734" end="28738" />
    <spannedText>cell</spannedText>
  </annotation>
  <annotation>
    <mention id="GO_CC_2016_02_16_test_Instance_10729" />
    <annotator id="GO_CC_2016_02_16_test_Instance_10000">Mike Bada, University of Colorado Anschutz Medical Campus</annotator>
    <span start="28801" end="28805" />
    <spannedText>cell</spannedText>
  </annotation>
  <annotation>
    <mention id="GO_CC_2016_02_16_test_Instance_10731" />
    <annotator id="GO_CC_2016_02_16_test_Instance_10000">Mike Bada, University of Colorado Anschutz Medical Campus</annotator>
    <span start="28853" end="28857" />
    <spannedText>cell</spannedText>
  </annotation>
  <annotation>
    <mention id="GO_CC_2016_02_16_test_Instance_10733" />
    <annotator id="GO_CC_2016_02_16_test_Instance_10000">Mike Bada, University of Colorado Anschutz Medical Campus</annotator>
    <span start="28874" end="28878" />
    <spannedText>cell</spannedText>
  </annotation>
  <annotation>
    <mention id="GO_CC_2016_02_16_test_Instance_10735" />
    <annotator id="GO_CC_2016_02_16_test_Instance_10000">Mike Bada, University of Colorado Anschutz Medical Campus</annotator>
    <span start="29327" end="29331" />
    <spannedText>cell</spannedText>
  </annotation>
  <annotation>
    <mention id="GO_CC_2016_02_16_test_Instance_10737" />
    <annotator id="GO_CC_2016_02_16_test_Instance_10000">Mike Bada, University of Colorado Anschutz Medical Campus</annotator>
    <span start="29831" end="29839" />
    <spannedText>cellular</spannedText>
  </annotation>
  <annotation>
    <mention id="GO_CC_2016_02_16_test_Instance_10739" />
    <annotator id="GO_CC_2016_02_16_test_Instance_10000">Mike Bada, University of Colorado Anschutz Medical Campus</annotator>
    <span start="29935" end="29940" />
    <spannedText>cells</spannedText>
  </annotation>
  <annotation>
    <mention id="GO_CC_2016_02_16_test_Instance_10741" />
    <annotator id="GO_CC_2016_02_16_test_Instance_10000">Mike Bada, University of Colorado Anschutz Medical Campus</annotator>
    <span start="30096" end="30101" />
    <spannedText>cells</spannedText>
  </annotation>
  <annotation>
    <mention id="GO_CC_2016_02_16_test_Instance_10743" />
    <annotator id="GO_CC_2016_02_16_test_Instance_10000">Mike Bada, University of Colorado Anschutz Medical Campus</annotator>
    <span start="30246" end="30251" />
    <spannedText>cells</spannedText>
  </annotation>
  <annotation>
    <mention id="GO_CC_2016_02_16_test_Instance_10745" />
    <annotator id="GO_CC_2016_02_16_test_Instance_10000">Mike Bada, University of Colorado Anschutz Medical Campus</annotator>
    <span start="30532" end="30536" />
    <spannedText>cell</spannedText>
  </annotation>
  <annotation>
    <mention id="GO_CC_2016_02_16_test_Instance_10747" />
    <annotator id="GO_CC_2016_02_16_test_Instance_10000">Mike Bada, University of Colorado Anschutz Medical Campus</annotator>
    <span start="30715" end="30720" />
    <spannedText>cells</spannedText>
  </annotation>
  <annotation>
    <mention id="GO_CC_2016_02_16_test_Instance_10751" />
    <annotator id="GO_CC_2016_02_16_test_Instance_10000">Mike Bada, University of Colorado Anschutz Medical Campus</annotator>
    <span start="30839" end="30843" />
    <spannedText>cell</spannedText>
  </annotation>
  <annotation>
    <mention id="GO_CC_2016_02_16_test_Instance_10755" />
    <annotator id="GO_CC_2016_02_16_test_Instance_10000">Mike Bada, University of Colorado Anschutz Medical Campus</annotator>
    <span start="31050" end="31055" />
    <spannedText>cells</spannedText>
  </annotation>
  <annotation>
    <mention id="GO_CC_2016_02_16_test_Instance_10757" />
    <annotator id="GO_CC_2016_02_16_test_Instance_10000">Mike Bada, University of Colorado Anschutz Medical Campus</annotator>
    <span start="31226" end="31231" />
    <spannedText>cells</spannedText>
  </annotation>
  <annotation>
    <mention id="GO_CC_2016_02_16_test_Instance_10759" />
    <annotator id="GO_CC_2016_02_16_test_Instance_10000">Mike Bada, University of Colorado Anschutz Medical Campus</annotator>
    <span start="31415" end="31419" />
    <spannedText>cell</spannedText>
  </annotation>
  <annotation>
    <mention id="GO_CC_2016_02_16_test_Instance_10761" />
    <annotator id="GO_CC_2016_02_16_test_Instance_10000">Mike Bada, University of Colorado Anschutz Medical Campus</annotator>
    <span start="31538" end="31542" />
    <spannedText>cell</spannedText>
  </annotation>
  <annotation>
    <mention id="GO_CC_2016_02_16_test_Instance_10763" />
    <annotator id="GO_CC_2016_02_16_test_Instance_10000">Mike Bada, University of Colorado Anschutz Medical Campus</annotator>
    <span start="31662" end="31666" />
    <spannedText>cell</spannedText>
  </annotation>
  <annotation>
    <mention id="GO_CC_2016_02_16_test_Instance_10765" />
    <annotator id="GO_CC_2016_02_16_test_Instance_10000">Mike Bada, University of Colorado Anschutz Medical Campus</annotator>
    <span start="32330" end="32335" />
    <spannedText>cells</spannedText>
  </annotation>
  <annotation>
    <mention id="GO_CC_2016_02_16_test_Instance_10767" />
    <annotator id="GO_CC_2016_02_16_test_Instance_10000">Mike Bada, University of Colorado Anschutz Medical Campus</annotator>
    <span start="32740" end="32745" />
    <spannedText>cells</spannedText>
  </annotation>
  <annotation>
    <mention id="GO_CC_2016_02_16_test_Instance_10769" />
    <annotator id="GO_CC_2016_02_16_test_Instance_10000">Mike Bada, University of Colorado Anschutz Medical Campus</annotator>
    <span start="32811" end="32816" />
    <spannedText>cells</spannedText>
  </annotation>
  <annotation>
    <mention id="GO_CC_2016_02_16_test_Instance_10771" />
    <annotator id="GO_CC_2016_02_16_test_Instance_10000">Mike Bada, University of Colorado Anschutz Medical Campus</annotator>
    <span start="32907" end="32912" />
    <spannedText>cells</spannedText>
  </annotation>
  <annotation>
    <mention id="GO_CC_2016_02_16_test_Instance_10773" />
    <annotator id="GO_CC_2016_02_16_test_Instance_10000">Mike Bada, University of Colorado Anschutz Medical Campus</annotator>
    <span start="33035" end="33039" />
    <spannedText>cell</spannedText>
  </annotation>
  <annotation>
    <mention id="GO_CC_2016_02_16_test_Instance_10775" />
    <annotator id="GO_CC_2016_02_16_test_Instance_10000">Mike Bada, University of Colorado Anschutz Medical Campus</annotator>
    <span start="33105" end="33109" />
    <spannedText>cell</spannedText>
  </annotation>
  <annotation>
    <mention id="GO_CC_2016_02_16_test_Instance_10777" />
    <annotator id="GO_CC_2016_02_16_test_Instance_10000">Mike Bada, University of Colorado Anschutz Medical Campus</annotator>
    <span start="1566" end="1570" />
    <spannedText>cell</spannedText>
  </annotation>
  <annotation>
    <mention id="GO_CC_2016_02_16_test_Instance_25909" />
    <annotator id="GO_CC_2016_02_16_test_Instance_10000">Mike Bada, University of Colorado Anschutz Medical Campus</annotator>
    <span start="4064" end="4078" />
    <spannedText>actin filament</spannedText>
  </annotation>
  <annotation>
    <mention id="GO_CC_2016_02_16_test_Instance_25911" />
    <annotator id="GO_CC_2016_02_16_test_Instance_10000">Mike Bada, University of Colorado Anschutz Medical Campus</annotator>
    <span start="4317" end="4347" />
    <spannedText>type III intermediate filament</spannedText>
  </annotation>
  <annotation>
    <mention id="GO_CC_2016_02_16_test_Instance_25913" />
    <annotator id="GO_CC_2016_02_16_test_Instance_10000">Mike Bada, University of Colorado Anschutz Medical Campus</annotator>
    <span start="4838" end="4844" />
    <spannedText>nuclei</spannedText>
  </annotation>
  <annotation>
    <mention id="GO_CC_2016_02_16_test_Instance_25915" />
    <annotator id="GO_CC_2016_02_16_test_Instance_10000">Mike Bada, University of Colorado Anschutz Medical Campus</annotator>
    <span start="4888" end="4895" />
    <spannedText>nucleus</spannedText>
  </annotation>
  <annotation>
    <mention id="GO_CC_2016_02_16_test_Instance_25917" />
    <annotator id="GO_CC_2016_02_16_test_Instance_10000">Mike Bada, University of Colorado Anschutz Medical Campus</annotator>
    <span start="4904" end="4911" />
    <spannedText>nuclear</spannedText>
  </annotation>
  <annotation>
    <mention id="GO_CC_2016_02_16_test_Instance_25919" />
    <annotator id="GO_CC_2016_02_16_test_Instance_10000">Mike Bada, University of Colorado Anschutz Medical Campus</annotator>
    <span start="8893" end="8902" />
    <spannedText>membranes</spannedText>
  </annotation>
  <annotation>
    <mention id="GO_CC_2016_02_16_test_Instance_25925" />
    <annotator id="GO_CC_2016_02_16_test_Instance_10000">Mike Bada, University of Colorado Anschutz Medical Campus</annotator>
    <span start="13079" end="13085" />
    <spannedText>nuclei</spannedText>
  </annotation>
  <annotation>
    <mention id="GO_CC_2016_02_16_test_Instance_25927" />
    <annotator id="GO_CC_2016_02_16_test_Instance_10000">Mike Bada, University of Colorado Anschutz Medical Campus</annotator>
    <span start="13185" end="13196" />
    <spannedText>Cell nuclei</spannedText>
  </annotation>
  <annotation>
    <mention id="GO_CC_2016_02_16_test_Instance_25929" />
    <annotator id="GO_CC_2016_02_16_test_Instance_10000">Mike Bada, University of Colorado Anschutz Medical Campus</annotator>
    <span start="14698" end="14706" />
    <spannedText>membrane</spannedText>
  </annotation>
  <annotation>
    <mention id="GO_CC_2016_02_16_test_Instance_25931" />
    <annotator id="GO_CC_2016_02_16_test_Instance_10000">Mike Bada, University of Colorado Anschutz Medical Campus</annotator>
    <span start="14976" end="14982" />
    <spannedText>nuclei</spannedText>
  </annotation>
  <annotation>
    <mention id="GO_CC_2016_02_16_test_Instance_25933" />
    <annotator id="GO_CC_2016_02_16_test_Instance_10000">Mike Bada, University of Colorado Anschutz Medical Campus</annotator>
    <span start="15234" end="15242" />
    <spannedText>membrane</spannedText>
  </annotation>
  <annotation>
    <mention id="GO_CC_2016_02_16_test_Instance_25935" />
    <annotator id="GO_CC_2016_02_16_test_Instance_10000">Mike Bada, University of Colorado Anschutz Medical Campus</annotator>
    <span start="15839" end="15845" />
    <spannedText>nuclei</spannedText>
  </annotation>
  <annotation>
    <mention id="GO_CC_2016_02_16_test_Instance_25937" />
    <annotator id="GO_CC_2016_02_16_test_Instance_10000">Mike Bada, University of Colorado Anschutz Medical Campus</annotator>
    <span start="16221" end="16228" />
    <spannedText>nuclear</spannedText>
  </annotation>
  <annotation>
    <mention id="GO_CC_2016_02_16_test_Instance_25939" />
    <annotator id="GO_CC_2016_02_16_test_Instance_10000">Mike Bada, University of Colorado Anschutz Medical Campus</annotator>
    <span start="16525" end="16532" />
    <spannedText>nuclear</spannedText>
  </annotation>
  <annotation>
    <mention id="GO_CC_2016_02_16_test_Instance_25941" />
    <annotator id="GO_CC_2016_02_16_test_Instance_10000">Mike Bada, University of Colorado Anschutz Medical Campus</annotator>
    <span start="16543" end="16550" />
    <spannedText>nuclear</spannedText>
  </annotation>
  <annotation>
    <mention id="GO_CC_2016_02_16_test_Instance_25943" />
    <annotator id="GO_CC_2016_02_16_test_Instance_10000">Mike Bada, University of Colorado Anschutz Medical Campus</annotator>
    <span start="16863" end="16872" />
    <spannedText>membranes</spannedText>
  </annotation>
  <annotation>
    <mention id="GO_CC_2016_02_16_test_Instance_25945" />
    <annotator id="GO_CC_2016_02_16_test_Instance_10000">Mike Bada, University of Colorado Anschutz Medical Campus</annotator>
    <span start="17033" end="17042" />
    <spannedText>membranes</spannedText>
  </annotation>
  <annotation>
    <mention id="GO_CC_2016_02_16_test_Instance_25947" />
    <annotator id="GO_CC_2016_02_16_test_Instance_10000">Mike Bada, University of Colorado Anschutz Medical Campus</annotator>
    <span start="17238" end="17246" />
    <spannedText>membrane</spannedText>
  </annotation>
  <annotation>
    <mention id="GO_CC_2016_02_16_test_Instance_25949" />
    <annotator id="GO_CC_2016_02_16_test_Instance_10000">Mike Bada, University of Colorado Anschutz Medical Campus</annotator>
    <span start="17308" end="17316" />
    <spannedText>vacuoles</spannedText>
  </annotation>
  <annotation>
    <mention id="GO_CC_2016_02_16_test_Instance_25951" />
    <annotator id="GO_CC_2016_02_16_test_Instance_10000">Mike Bada, University of Colorado Anschutz Medical Campus</annotator>
    <span start="17436" end="17445" />
    <spannedText>membranes</spannedText>
  </annotation>
  <annotation>
    <mention id="GO_CC_2016_02_16_test_Instance_25953" />
    <annotator id="GO_CC_2016_02_16_test_Instance_10000">Mike Bada, University of Colorado Anschutz Medical Campus</annotator>
    <span start="18085" end="18091" />
    <spannedText>nuclei</spannedText>
  </annotation>
  <annotation>
    <mention id="GO_CC_2016_02_16_test_Instance_25957" />
    <annotator id="GO_CC_2016_02_16_test_Instance_10000">Mike Bada, University of Colorado Anschutz Medical Campus</annotator>
    <span start="20520" end="20532" />
    <spannedText>cell surface</spannedText>
  </annotation>
  <annotation>
    <mention id="GO_CC_2016_02_16_test_Instance_25959" />
    <annotator id="GO_CC_2016_02_16_test_Instance_10000">Mike Bada, University of Colorado Anschutz Medical Campus</annotator>
    <span start="21173" end="21185" />
    <spannedText>cell surface</spannedText>
  </annotation>
  <annotation>
    <mention id="GO_CC_2016_02_16_test_Instance_25961" />
    <annotator id="GO_CC_2016_02_16_test_Instance_10000">Mike Bada, University of Colorado Anschutz Medical Campus</annotator>
    <span start="21310" end="21319" />
    <spannedText>membranes</spannedText>
  </annotation>
  <annotation>
    <mention id="GO_CC_2016_02_16_test_Instance_25963" />
    <annotator id="GO_CC_2016_02_16_test_Instance_10000">Mike Bada, University of Colorado Anschutz Medical Campus</annotator>
    <span start="24518" end="24525" />
    <spannedText>nucleus</spannedText>
  </annotation>
  <annotation>
    <mention id="GO_CC_2016_02_16_test_Instance_25965" />
    <annotator id="GO_CC_2016_02_16_test_Instance_10000">Mike Bada, University of Colorado Anschutz Medical Campus</annotator>
    <span start="24551" end="24561" />
    <spannedText>organelles</spannedText>
  </annotation>
  <annotation>
    <mention id="GO_CC_2016_02_16_test_Instance_25967" />
    <annotator id="GO_CC_2016_02_16_test_Instance_10000">Mike Bada, University of Colorado Anschutz Medical Campus</annotator>
    <span start="24626" end="24632" />
    <spannedText>nuclei</spannedText>
  </annotation>
  <annotation>
    <mention id="GO_CC_2016_02_16_test_Instance_25969" />
    <annotator id="GO_CC_2016_02_16_test_Instance_10000">Mike Bada, University of Colorado Anschutz Medical Campus</annotator>
    <span start="24637" end="24647" />
    <spannedText>organelles</spannedText>
  </annotation>
  <annotation>
    <mention id="GO_CC_2016_02_16_test_Instance_25971" />
    <annotator id="GO_CC_2016_02_16_test_Instance_10000">Mike Bada, University of Colorado Anschutz Medical Campus</annotator>
    <span start="25428" end="25439" />
    <spannedText>cell nuclei</spannedText>
  </annotation>
  <annotation>
    <mention id="GO_CC_2016_02_16_test_Instance_25973" />
    <annotator id="GO_CC_2016_02_16_test_Instance_10000">Mike Bada, University of Colorado Anschutz Medical Campus</annotator>
    <span start="25480" end="25491" />
    <spannedText>cell nuclei</spannedText>
  </annotation>
  <annotation>
    <mention id="GO_CC_2016_02_16_test_Instance_25975" />
    <annotator id="GO_CC_2016_02_16_test_Instance_10000">Mike Bada, University of Colorado Anschutz Medical Campus</annotator>
    <span start="25570" end="25581" />
    <spannedText>cell nuclei</spannedText>
  </annotation>
  <annotation>
    <mention id="GO_CC_2016_02_16_test_Instance_25977" />
    <annotator id="GO_CC_2016_02_16_test_Instance_10000">Mike Bada, University of Colorado Anschutz Medical Campus</annotator>
    <span start="28749" end="28759" />
    <spannedText>organelles</spannedText>
  </annotation>
  <annotation>
    <mention id="GO_CC_2016_02_16_test_Instance_25979" />
    <annotator id="GO_CC_2016_02_16_test_Instance_10000">Mike Bada, University of Colorado Anschutz Medical Campus</annotator>
    <span start="30788" end="30800" />
    <spannedText>cell nucleus</spannedText>
  </annotation>
  <annotation>
    <mention id="GO_CC_2016_02_16_test_Instance_25981" />
    <annotator id="GO_CC_2016_02_16_test_Instance_10000">Mike Bada, University of Colorado Anschutz Medical Campus</annotator>
    <span start="30898" end="30909" />
    <spannedText>cell nuclei</spannedText>
  </annotation>
  <annotation>
    <mention id="GO_CC_2016_02_16_test_Instance_25983" />
    <annotator id="GO_CC_2016_02_16_test_Instance_10000">Mike Bada, University of Colorado Anschutz Medical Campus</annotator>
    <span start="31110" end="31116" />
    <spannedText>nuclei</spannedText>
  </annotation>
  <annotation>
    <mention id="GO_CC_2016_02_16_test_Instance_25985" />
    <annotator id="GO_CC_2016_02_16_test_Instance_10000">Mike Bada, University of Colorado Anschutz Medical Campus</annotator>
    <span start="31171" end="31178" />
    <spannedText>nucleus</spannedText>
  </annotation>
  <annotation>
    <mention id="GO_CC_2016_02_16_test_Instance_25987" />
    <annotator id="GO_CC_2016_02_16_test_Instance_10000">Mike Bada, University of Colorado Anschutz Medical Campus</annotator>
    <span start="31647" end="31654" />
    <spannedText>nucleus</spannedText>
  </annotation>
  <annotation>
    <mention id="GO_CC_2016_02_16_test_Instance_25989" />
    <annotator id="GO_CC_2016_02_16_test_Instance_10000">Mike Bada, University of Colorado Anschutz Medical Campus</annotator>
    <span start="31775" end="31781" />
    <spannedText>nuclei</spannedText>
  </annotation>
  <annotation>
    <mention id="GO_CC_2016_02_16_test_Instance_25991" />
    <annotator id="GO_CC_2016_02_16_test_Instance_10000">Mike Bada, University of Colorado Anschutz Medical Campus</annotator>
    <span start="31996" end="32003" />
    <spannedText>nucleus</spannedText>
  </annotation>
  <annotation>
    <mention id="GO_CC_2016_02_16_test_Instance_25993" />
    <annotator id="GO_CC_2016_02_16_test_Instance_10000">Mike Bada, University of Colorado Anschutz Medical Campus</annotator>
    <span start="32112" end="32124" />
    <spannedText>cytoskeletal</spannedText>
  </annotation>
  <annotation>
    <mention id="GO_CC_2016_02_16_test_Instance_25995" />
    <annotator id="GO_CC_2016_02_16_test_Instance_10000">Mike Bada, University of Colorado Anschutz Medical Campus</annotator>
    <span start="32231" end="32245" />
    <spannedText>Actin filament</spannedText>
  </annotation>
  <annotation>
    <mention id="GO_CC_2016_02_16_test_Instance_25997" />
    <annotator id="GO_CC_2016_02_16_test_Instance_10000">Mike Bada, University of Colorado Anschutz Medical Campus</annotator>
    <span start="32500" end="32530" />
    <spannedText>type III intermediate filament</spannedText>
  </annotation>
  <annotation>
    <mention id="GO_CC_2016_02_16_test_Instance_25999" />
    <annotator id="GO_CC_2016_02_16_test_Instance_10000">Mike Bada, University of Colorado Anschutz Medical Campus</annotator>
    <span start="32985" end="32997" />
    <spannedText>cytoskeleton</spannedText>
  </annotation>
  <annotation>
    <mention id="GO_CC_2016_02_16_test_Instance_26001" />
    <annotator id="GO_CC_2016_02_16_test_Instance_10000">Mike Bada, University of Colorado Anschutz Medical Campus</annotator>
    <span start="33244" end="33256" />
    <spannedText>cytoskeletal</spannedText>
  </annotation>
  <classMention id="GO_CC_2016_02_16_test_Instance_25933">
    <mentionClass id="GO:0016020">membrane</mentionClass>
  </classMention>
  <classMention id="GO_CC_2016_02_16_test_Instance_25931">
    <mentionClass id="GO:0005634">nucleus</mentionClass>
  </classMention>
  <classMention id="GO_CC_2016_02_16_test_Instance_25929">
    <mentionClass id="GO:0016020">membrane</mentionClass>
  </classMention>
  <classMention id="GO_CC_2016_02_16_test_Instance_25927">
    <mentionClass id="GO:0005634">nucleus</mentionClass>
  </classMention>
  <classMention id="GO_CC_2016_02_16_test_Instance_25941">
    <mentionClass id="GO:0005634">nucleus</mentionClass>
  </classMention>
  <classMention id="GO_CC_2016_02_16_test_Instance_25939">
    <mentionClass id="GO:0005634">nucleus</mentionClass>
  </classMention>
  <classMention id="GO_CC_2016_02_16_test_Instance_25937">
    <mentionClass id="GO:0005634">nucleus</mentionClass>
  </classMention>
  <classMention id="GO_CC_2016_02_16_test_Instance_25935">
    <mentionClass id="GO:0005634">nucleus</mentionClass>
  </classMention>
  <classMention id="GO_CC_2016_02_16_test_Instance_25949">
    <mentionClass id="GO:0005773">vacuole</mentionClass>
  </classMention>
  <classMention id="GO_CC_2016_02_16_Instance_190003">
    <mentionClass id="GO:0005615">extracellular space</mentionClass>
  </classMention>
  <classMention id="GO_CC_2016_02_16_test_Instance_25947">
    <mentionClass id="GO:0016020">membrane</mentionClass>
  </classMention>
  <classMention id="GO_CC_2016_02_16_test_Instance_25945">
    <mentionClass id="GO:0016020">membrane</mentionClass>
  </classMention>
  <classMention id="GO_CC_2016_02_16_test_Instance_25943">
    <mentionClass id="GO:0016020">membrane</mentionClass>
  </classMention>
  <classMention id="GO_CC_2016_02_16_test_Instance_25959">
    <mentionClass id="GO:0009986">cell surface</mentionClass>
  </classMention>
  <classMention id="GO_CC_2016_02_16_test_Instance_25957">
    <mentionClass id="GO:0009986">cell surface</mentionClass>
  </classMention>
  <classMention id="GO_CC_2016_02_16_test_Instance_25953">
    <mentionClass id="GO:0005634">nucleus</mentionClass>
  </classMention>
  <classMention id="GO_CC_2016_02_16_test_Instance_25951">
    <mentionClass id="GO:0016020">membrane</mentionClass>
  </classMention>
  <classMention id="GO_CC_2016_02_16_test_Instance_25967">
    <mentionClass id="GO:0005634">nucleus</mentionClass>
  </classMention>
  <classMention id="GO_CC_2016_02_16_test_Instance_25965">
    <mentionClass id="GO:0043226">organelle</mentionClass>
  </classMention>
  <classMention id="GO_CC_2016_02_16_test_Instance_25963">
    <mentionClass id="GO:0005634">nucleus</mentionClass>
  </classMention>
  <classMention id="GO_CC_2016_02_16_test_Instance_25961">
    <mentionClass id="GO:0016020">membrane</mentionClass>
  </classMention>
  <classMention id="GO_CC_2016_02_16_test_Instance_25975">
    <mentionClass id="GO:0005634">nucleus</mentionClass>
  </classMention>
  <classMention id="GO_CC_2016_02_16_Instance_102537">
    <mentionClass id="GO:0042995">cell projection</mentionClass>
  </classMention>
  <classMention id="GO_CC_2016_02_16_test_Instance_25973">
    <mentionClass id="GO:0005634">nucleus</mentionClass>
  </classMention>
  <classMention id="GO_CC_2016_02_16_Instance_102535">
    <mentionClass id="GO:0042995">cell projection</mentionClass>
  </classMention>
  <classMention id="GO_CC_2016_02_16_test_Instance_25971">
    <mentionClass id="GO:0005634">nucleus</mentionClass>
  </classMention>
  <classMention id="GO_CC_2016_02_16_test_Instance_25969">
    <mentionClass id="GO:0043226">organelle</mentionClass>
  </classMention>
  <classMention id="GO_CC_2016_02_16_test_Instance_10589">
    <mentionClass id="CL_GO_EXT:cell">cell</mentionClass>
  </classMention>
  <classMention id="GO_CC_2016_02_16_test_Instance_25983">
    <mentionClass id="GO:0005634">nucleus</mentionClass>
  </classMention>
  <classMention id="GO_CC_2016_02_16_test_Instance_10587">
    <mentionClass id="CL_GO_EXT:cell">cell</mentionClass>
  </classMention>
  <classMention id="GO_CC_2016_02_16_test_Instance_25981">
    <mentionClass id="GO:0005634">nucleus</mentionClass>
  </classMention>
  <classMention id="GO_CC_2016_02_16_test_Instance_25979">
    <mentionClass id="GO:0005634">nucleus</mentionClass>
  </classMention>
  <classMention id="GO_CC_2016_02_16_Instance_102541">
    <mentionClass id="GO:0042995">cell projection</mentionClass>
  </classMention>
  <classMention id="GO_CC_2016_02_16_test_Instance_25977">
    <mentionClass id="GO:0043226">organelle</mentionClass>
  </classMention>
  <classMention id="GO_CC_2016_02_16_Instance_102539">
    <mentionClass id="GO:0042995">cell projection</mentionClass>
  </classMention>
  <classMention id="GO_CC_2016_02_16_test_Instance_10597">
    <mentionClass id="CL_GO_EXT:cell">cell</mentionClass>
  </classMention>
  <classMention id="GO_CC_2016_02_16_test_Instance_25991">
    <mentionClass id="GO:0005634">nucleus</mentionClass>
  </classMention>
  <classMention id="GO_CC_2016_02_16_test_Instance_10595">
    <mentionClass id="CL_GO_EXT:cell">cell</mentionClass>
  </classMention>
  <classMention id="GO_CC_2016_02_16_test_Instance_25989">
    <mentionClass id="GO:0005634">nucleus</mentionClass>
  </classMention>
  <classMention id="GO_CC_2016_02_16_test_Instance_10593">
    <mentionClass id="CL_GO_EXT:cell">cell</mentionClass>
  </classMention>
  <classMention id="GO_CC_2016_02_16_test_Instance_25987">
    <mentionClass id="GO:0005634">nucleus</mentionClass>
  </classMention>
  <classMention id="GO_CC_2016_02_16_test_Instance_10591">
    <mentionClass id="CL_GO_EXT:cell">cell</mentionClass>
  </classMention>
  <classMention id="GO_CC_2016_02_16_test_Instance_25985">
    <mentionClass id="GO:0005634">nucleus</mentionClass>
  </classMention>
  <classMention id="GO_CC_2016_02_16_test_Instance_10605">
    <mentionClass id="CL_GO_EXT:cell">cell</mentionClass>
  </classMention>
  <classMention id="GO_CC_2016_02_16_test_Instance_25999">
    <mentionClass id="GO:0005856">cytoskeleton</mentionClass>
  </classMention>
  <classMention id="GO_CC_2016_02_16_test_Instance_10603">
    <mentionClass id="CL_GO_EXT:cell">cell</mentionClass>
  </classMention>
  <classMention id="GO_CC_2016_02_16_test_Instance_25997">
    <mentionClass id="GO:0045098">type III intermediate filament</mentionClass>
  </classMention>
  <classMention id="GO_CC_2016_02_16_test_Instance_10601">
    <mentionClass id="CL_GO_EXT:cell">cell</mentionClass>
  </classMention>
  <classMention id="GO_CC_2016_02_16_test_Instance_25995">
    <mentionClass id="GO:0005884">actin filament</mentionClass>
  </classMention>
  <classMention id="GO_CC_2016_02_16_test_Instance_10599">
    <mentionClass id="CL_GO_EXT:cell">cell</mentionClass>
  </classMention>
  <classMention id="GO_CC_2016_02_16_test_Instance_25993">
    <mentionClass id="GO:0005856">cytoskeleton</mentionClass>
  </classMention>
  <classMention id="GO_CC_2016_02_16_test_Instance_10613">
    <mentionClass id="CL_GO_EXT:cell">cell</mentionClass>
  </classMention>
  <classMention id="GO_CC_2016_02_16_test_Instance_10611">
    <mentionClass id="CL_GO_EXT:cell">cell</mentionClass>
  </classMention>
  <classMention id="GO_CC_2016_02_16_test_Instance_10609">
    <mentionClass id="CL_GO_EXT:cell">cell</mentionClass>
  </classMention>
  <classMention id="GO_CC_2016_02_16_test_Instance_26001">
    <mentionClass id="GO:0005856">cytoskeleton</mentionClass>
  </classMention>
  <classMention id="GO_CC_2016_02_16_test_Instance_10607">
    <mentionClass id="CL_GO_EXT:cell">cell</mentionClass>
  </classMention>
  <classMention id="GO_CC_2016_02_16_test_Instance_10623">
    <mentionClass id="CL_GO_EXT:cell">cell</mentionClass>
  </classMention>
  <classMention id="GO_CC_2016_02_16_test_Instance_10621">
    <mentionClass id="CL_GO_EXT:cell">cell</mentionClass>
  </classMention>
  <classMention id="GO_CC_2016_02_16_test_Instance_10619">
    <mentionClass id="CL_GO_EXT:cell">cell</mentionClass>
  </classMention>
  <classMention id="GO_CC_2016_02_16_test_Instance_10617">
    <mentionClass id="CL_GO_EXT:cell">cell</mentionClass>
  </classMention>
  <classMention id="GO_CC_2016_02_16_test_Instance_10631">
    <mentionClass id="CL_GO_EXT:cell">cell</mentionClass>
  </classMention>
  <classMention id="GO_CC_2016_02_16_test_Instance_10629">
    <mentionClass id="CL_GO_EXT:cell">cell</mentionClass>
  </classMention>
  <classMention id="GO_CC_2016_02_16_test_Instance_10627">
    <mentionClass id="CL_GO_EXT:cell">cell</mentionClass>
  </classMention>
  <classMention id="GO_CC_2016_02_16_test_Instance_10625">
    <mentionClass id="CL_GO_EXT:cell">cell</mentionClass>
  </classMention>
  <classMention id="GO_CC_2016_02_16_test_Instance_10639">
    <mentionClass id="CL_GO_EXT:cell">cell</mentionClass>
  </classMention>
  <classMention id="GO_CC_2016_02_16_test_Instance_10637">
    <mentionClass id="CL_GO_EXT:cell">cell</mentionClass>
  </classMention>
  <classMention id="GO_CC_2016_02_16_test_Instance_10635">
    <mentionClass id="CL_GO_EXT:cell">cell</mentionClass>
  </classMention>
  <classMention id="GO_CC_2016_02_16_test_Instance_10633">
    <mentionClass id="CL_GO_EXT:cell">cell</mentionClass>
  </classMention>
  <classMention id="GO_CC_2016_02_16_Instance_101571">
    <mentionClass id="GO:0005634">nucleus</mentionClass>
  </classMention>
  <classMention id="GO_CC_2016_02_16_test_Instance_10647">
    <mentionClass id="CL_GO_EXT:cell">cell</mentionClass>
  </classMention>
  <classMention id="GO_CC_2016_02_16_test_Instance_10645">
    <mentionClass id="CL_GO_EXT:cell">cell</mentionClass>
  </classMention>
  <classMention id="GO_CC_2016_02_16_test_Instance_10643">
    <mentionClass id="CL_GO_EXT:cell">cell</mentionClass>
  </classMention>
  <classMention id="GO_CC_2016_02_16_test_Instance_10641">
    <mentionClass id="CL_GO_EXT:cell">cell</mentionClass>
  </classMention>
  <classMention id="GO_CC_2016_02_16_Instance_101579">
    <mentionClass id="GO:0005634">nucleus</mentionClass>
  </classMention>
  <classMention id="GO_CC_2016_02_16_test_Instance_10655">
    <mentionClass id="CL_GO_EXT:cell">cell</mentionClass>
  </classMention>
  <classMention id="GO_CC_2016_02_16_Instance_101577">
    <mentionClass id="GO:0005634">nucleus</mentionClass>
  </classMention>
  <classMention id="GO_CC_2016_02_16_test_Instance_10653">
    <mentionClass id="CL_GO_EXT:cell">cell</mentionClass>
  </classMention>
  <classMention id="GO_CC_2016_02_16_Instance_101575">
    <mentionClass id="GO:0005634">nucleus</mentionClass>
  </classMention>
  <classMention id="GO_CC_2016_02_16_test_Instance_10651">
    <mentionClass id="CL_GO_EXT:cell">cell</mentionClass>
  </classMention>
  <classMention id="GO_CC_2016_02_16_Instance_101573">
    <mentionClass id="GO:0005634">nucleus</mentionClass>
  </classMention>
  <classMention id="GO_CC_2016_02_16_test_Instance_10649">
    <mentionClass id="CL_GO_EXT:cell">cell</mentionClass>
  </classMention>
  <classMention id="GO_CC_2016_02_16_Instance_101587">
    <mentionClass id="GO:0005634">nucleus</mentionClass>
  </classMention>
  <classMention id="GO_CC_2016_02_16_test_Instance_10667">
    <mentionClass id="CL_GO_EXT:cell">cell</mentionClass>
  </classMention>
  <classMention id="GO_CC_2016_02_16_Instance_101585">
    <mentionClass id="GO:0005634">nucleus</mentionClass>
  </classMention>
  <classMention id="GO_CC_2016_02_16_test_Instance_10663">
    <mentionClass id="CL_GO_EXT:cell">cell</mentionClass>
  </classMention>
  <classMention id="GO_CC_2016_02_16_Instance_101583">
    <mentionClass id="GO:0005634">nucleus</mentionClass>
  </classMention>
  <classMention id="GO_CC_2016_02_16_test_Instance_10661">
    <mentionClass id="CL_GO_EXT:cell">cell</mentionClass>
  </classMention>
  <classMention id="GO_CC_2016_02_16_Instance_101581">
    <mentionClass id="GO:0005634">nucleus</mentionClass>
  </classMention>
  <classMention id="GO_CC_2016_02_16_test_Instance_10659">
    <mentionClass id="CL_GO_EXT:cell">cell</mentionClass>
  </classMention>
  <classMention id="GO_CC_2016_02_16_Instance_101595">
    <mentionClass id="GO:0005634">nucleus</mentionClass>
  </classMention>
  <classMention id="GO_CC_2016_02_16_test_Instance_10675">
    <mentionClass id="CL_GO_EXT:cell">cell</mentionClass>
  </classMention>
  <classMention id="GO_CC_2016_02_16_Instance_101593">
    <mentionClass id="GO:0005634">nucleus</mentionClass>
  </classMention>
  <classMention id="GO_CC_2016_02_16_test_Instance_10673">
    <mentionClass id="CL_GO_EXT:cell">cell</mentionClass>
  </classMention>
  <classMention id="GO_CC_2016_02_16_Instance_101591">
    <mentionClass id="GO:0005634">nucleus</mentionClass>
  </classMention>
  <classMention id="GO_CC_2016_02_16_test_Instance_10671">
    <mentionClass id="CL_GO_EXT:cell">cell</mentionClass>
  </classMention>
  <classMention id="GO_CC_2016_02_16_Instance_101589">
    <mentionClass id="GO:0005634">nucleus</mentionClass>
  </classMention>
  <classMention id="GO_CC_2016_02_16_test_Instance_10669">
    <mentionClass id="CL_GO_EXT:cell">cell</mentionClass>
  </classMention>
  <classMention id="GO_CC_2016_02_16_test_Instance_10683">
    <mentionClass id="CL_GO_EXT:cell">cell</mentionClass>
  </classMention>
  <classMention id="GO_CC_2016_02_16_Instance_101601">
    <mentionClass id="GO:0005634">nucleus</mentionClass>
  </classMention>
  <classMention id="GO_CC_2016_02_16_test_Instance_10681">
    <mentionClass id="CL_GO_EXT:cell">cell</mentionClass>
  </classMention>
  <classMention id="GO_CC_2016_02_16_Instance_101599">
    <mentionClass id="GO:0005634">nucleus</mentionClass>
  </classMention>
  <classMention id="GO_CC_2016_02_16_test_Instance_10679">
    <mentionClass id="CL_GO_EXT:cell">cell</mentionClass>
  </classMention>
  <classMention id="GO_CC_2016_02_16_Instance_101597">
    <mentionClass id="GO:0005634">nucleus</mentionClass>
  </classMention>
  <classMention id="GO_CC_2016_02_16_test_Instance_10677">
    <mentionClass id="CL_GO_EXT:cell">cell</mentionClass>
  </classMention>
  <classMention id="GO_CC_2016_02_16_test_Instance_10691">
    <mentionClass id="CL_GO_EXT:cell">cell</mentionClass>
  </classMention>
  <classMention id="GO_CC_2016_02_16_test_Instance_10689">
    <mentionClass id="CL_GO_EXT:cell">cell</mentionClass>
  </classMention>
  <classMention id="GO_CC_2016_02_16_test_Instance_10687">
    <mentionClass id="CL_GO_EXT:cell">cell</mentionClass>
  </classMention>
  <classMention id="GO_CC_2016_02_16_test_Instance_10685">
    <mentionClass id="CL_GO_EXT:cell">cell</mentionClass>
  </classMention>
  <classMention id="GO_CC_2016_02_16_test_Instance_10705">
    <mentionClass id="CL_GO_EXT:cell">cell</mentionClass>
  </classMention>
  <classMention id="GO_CC_2016_02_16_test_Instance_10697">
    <mentionClass id="CL_GO_EXT:cell">cell</mentionClass>
  </classMention>
  <classMention id="GO_CC_2016_02_16_test_Instance_10695">
    <mentionClass id="CL_GO_EXT:cell">cell</mentionClass>
  </classMention>
  <classMention id="GO_CC_2016_02_16_test_Instance_10693">
    <mentionClass id="CL_GO_EXT:cell">cell</mentionClass>
  </classMention>
  <classMention id="GO_CC_2016_02_16_test_Instance_10713">
    <mentionClass id="CL_GO_EXT:cell">cell</mentionClass>
  </classMention>
  <classMention id="GO_CC_2016_02_16_test_Instance_10711">
    <mentionClass id="CL_GO_EXT:cell">cell</mentionClass>
  </classMention>
  <classMention id="GO_CC_2016_02_16_test_Instance_10709">
    <mentionClass id="CL_GO_EXT:cell">cell</mentionClass>
  </classMention>
  <classMention id="GO_CC_2016_02_16_test_Instance_10707">
    <mentionClass id="CL_GO_EXT:cell">cell</mentionClass>
  </classMention>
  <classMention id="GO_CC_2016_02_16_test_Instance_10721">
    <mentionClass id="CL_GO_EXT:cell">cell</mentionClass>
  </classMention>
  <classMention id="GO_CC_2016_02_16_Instance_101679">
    <mentionClass id="CL_GO_EXT:cell">cell</mentionClass>
  </classMention>
  <classMention id="GO_CC_2016_02_16_test_Instance_10719">
    <mentionClass id="CL_GO_EXT:cell">cell</mentionClass>
  </classMention>
  <classMention id="GO_CC_2016_02_16_test_Instance_10717">
    <mentionClass id="CL_GO_EXT:cell">cell</mentionClass>
  </classMention>
  <classMention id="GO_CC_2016_02_16_test_Instance_10091">
    <mentionClass id="CL_GO_EXT:cell">cell</mentionClass>
  </classMention>
  <classMention id="GO_CC_2016_02_16_test_Instance_10715">
    <mentionClass id="CL_GO_EXT:cell">cell</mentionClass>
  </classMention>
  <classMention id="GO_CC_2016_02_16_test_Instance_10729">
    <mentionClass id="CL_GO_EXT:cell">cell</mentionClass>
  </classMention>
  <classMention id="GO_CC_2016_02_16_test_Instance_10727">
    <mentionClass id="CL_GO_EXT:cell">cell</mentionClass>
  </classMention>
  <classMention id="GO_CC_2016_02_16_Instance_133">
    <mentionClass id="GO:0016020">membrane</mentionClass>
  </classMention>
  <classMention id="GO_CC_2016_02_16_test_Instance_10725">
    <mentionClass id="CL_GO_EXT:cell">cell</mentionClass>
  </classMention>
  <classMention id="GO_CC_2016_02_16_test_Instance_10723">
    <mentionClass id="CL_GO_EXT:cell">cell</mentionClass>
  </classMention>
  <classMention id="GO_CC_2016_02_16_test_Instance_10737">
    <mentionClass id="CL_GO_EXT:cell">cell</mentionClass>
  </classMention>
  <classMention id="GO_CC_2016_02_16_test_Instance_10735">
    <mentionClass id="CL_GO_EXT:cell">cell</mentionClass>
  </classMention>
  <classMention id="GO_CC_2016_02_16_Instance_145">
    <mentionClass id="CL_GO_EXT:cell">cell</mentionClass>
  </classMention>
  <classMention id="GO_CC_2016_02_16_test_Instance_10733">
    <mentionClass id="CL_GO_EXT:cell">cell</mentionClass>
  </classMention>
  <classMention id="GO_CC_2016_02_16_Instance_143">
    <mentionClass id="GO:0032991">macromolecular complex</mentionClass>
  </classMention>
  <classMention id="GO_CC_2016_02_16_test_Instance_10731">
    <mentionClass id="CL_GO_EXT:cell">cell</mentionClass>
  </classMention>
  <classMention id="GO_CC_2016_02_16_test_Instance_10745">
    <mentionClass id="CL_GO_EXT:cell">cell</mentionClass>
  </classMention>
  <classMention id="GO_CC_2016_02_16_test_Instance_10743">
    <mentionClass id="CL_GO_EXT:cell">cell</mentionClass>
  </classMention>
  <classMention id="GO_CC_2016_02_16_test_Instance_10741">
    <mentionClass id="CL_GO_EXT:cell">cell</mentionClass>
  </classMention>
  <classMention id="GO_CC_2016_02_16_test_Instance_10739">
    <mentionClass id="CL_GO_EXT:cell">cell</mentionClass>
  </classMention>
  <classMention id="GO_CC_2016_02_16_test_Instance_10757">
    <mentionClass id="CL_GO_EXT:cell">cell</mentionClass>
  </classMention>
  <classMention id="GO_CC_2016_02_16_test_Instance_10755">
    <mentionClass id="CL_GO_EXT:cell">cell</mentionClass>
  </classMention>
  <classMention id="GO_CC_2016_02_16_test_Instance_10751">
    <mentionClass id="CL_GO_EXT:cell">cell</mentionClass>
  </classMention>
  <classMention id="GO_CC_2016_02_16_test_Instance_10747">
    <mentionClass id="CL_GO_EXT:cell">cell</mentionClass>
  </classMention>
  <classMention id="GO_CC_2016_02_16_test_Instance_10765">
    <mentionClass id="CL_GO_EXT:cell">cell</mentionClass>
  </classMention>
  <classMention id="GO_CC_2016_02_16_test_Instance_10763">
    <mentionClass id="CL_GO_EXT:cell">cell</mentionClass>
  </classMention>
  <classMention id="GO_CC_2016_02_16_test_Instance_10761">
    <mentionClass id="CL_GO_EXT:cell">cell</mentionClass>
  </classMention>
  <classMention id="GO_CC_2016_02_16_test_Instance_10759">
    <mentionClass id="CL_GO_EXT:cell">cell</mentionClass>
  </classMention>
  <classMention id="GO_CC_2016_02_16_test_Instance_10773">
    <mentionClass id="CL_GO_EXT:cell">cell</mentionClass>
  </classMention>
  <classMention id="GO_CC_2016_02_16_test_Instance_10771">
    <mentionClass id="CL_GO_EXT:cell">cell</mentionClass>
  </classMention>
  <classMention id="GO_CC_2016_02_16_test_Instance_10769">
    <mentionClass id="CL_GO_EXT:cell">cell</mentionClass>
  </classMention>
  <classMention id="GO_CC_2016_02_16_test_Instance_10767">
    <mentionClass id="CL_GO_EXT:cell">cell</mentionClass>
  </classMention>
  <classMention id="GO_CC_2016_02_16_test_Instance_10777">
    <mentionClass id="CL_GO_EXT:cell">cell</mentionClass>
  </classMention>
  <classMention id="GO_CC_2016_02_16_test_Instance_10775">
    <mentionClass id="CL_GO_EXT:cell">cell</mentionClass>
  </classMention>
  <classMention id="GO_CC_2016_02_16_test_Instance_25913">
    <mentionClass id="GO:0005634">nucleus</mentionClass>
  </classMention>
  <classMention id="GO_CC_2016_02_16_test_Instance_25911">
    <mentionClass id="GO:0045098">type III intermediate filament</mentionClass>
  </classMention>
  <classMention id="GO_CC_2016_02_16_test_Instance_25909">
    <mentionClass id="GO:0005884">actin filament</mentionClass>
  </classMention>
  <classMention id="GO_CC_2016_02_16_test_Instance_25925">
    <mentionClass id="GO:0005634">nucleus</mentionClass>
  </classMention>
  <classMention id="GO_CC_2016_02_16_test_Instance_25919">
    <mentionClass id="GO:0016020">membrane</mentionClass>
  </classMention>
  <classMention id="GO_CC_2016_02_16_test_Instance_25917">
    <mentionClass id="GO:0005634">nucleus</mentionClass>
  </classMention>
  <classMention id="GO_CC_2016_02_16_test_Instance_25915">
    <mentionClass id="GO:0005634">nucleus</mentionClass>
  </classMention>
</annotations>

