<?xml version="1.0" encoding="UTF-8" standalone="no"?>
<knowtator-project>
    <document id="17244351" text-file="17244351.txt">
        <annotation annotator="Mike Bada, University of Colorado Anschutz Medical Campus" id="CL_basic_2014_02_21_Instance_10009" type="identity">
            <class id="CL_GO_EXT:cell"/>
            <span end="4094" id="17244351-11298" start="4089">cells</span>
        </annotation>
        <annotation annotator="Mike Bada, University of Colorado Anschutz Medical Campus" id="CL_basic_2014_02_21_Instance_12413" type="identity">
            <class id="CL:0000081"/>
            <span end="4457" id="17244351-11304" start="4446">blood cells</span>
        </annotation>
        <annotation annotator="Mike Bada, University of Colorado Anschutz Medical Campus" id="CL_basic_2014_02_21_plus_nested_Instance_50463" type="identity">
            <class id="CL_GO_EXT:cell"/>
            <span end="16488" id="17244351-11320" start="16480">cellular</span>
        </annotation>
        <annotation annotator="Mike Bada, University of Colorado Anschutz Medical Campus" id="CL_basic_2014_02_21_plus_nested_Instance_50541" type="identity">
            <class id="CL_GO_EXT:cell"/>
            <span end="16625" id="17244351-11322" start="16617">cellular</span>
        </annotation>
        <annotation annotator="Mike Bada, University of Colorado Anschutz Medical Campus" id="CL_basic_2014_02_21_Instance_12421" type="identity">
            <class id="CL:0000542"/>
            <span end="16817" id="17244351-11306" start="16807">lymphocyte</span>
        </annotation>
        <annotation annotator="Mike Bada, University of Colorado Anschutz Medical Campus" id="CL_basic_2014_02_21_Instance_12425" type="identity">
            <class id="CL:0000084"/>
            <span end="16839" id="17244351-11308" start="16833">T cell</span>
        </annotation>
        <annotation annotator="Mike Bada, University of Colorado Anschutz Medical Campus" id="CL_basic_2014_02_21_Instance_12429" type="identity">
            <class id="CL:0000542"/>
            <span end="20755" id="17244351-11310" start="20745">lymphocyte</span>
        </annotation>
        <annotation annotator="Mike Bada, University of Colorado Anschutz Medical Campus" id="CL_basic_2014_02_21_Instance_12431" type="identity">
            <class id="CL:0000542"/>
            <span end="20862" id="17244351-11312" start="20852">lymphocyte</span>
        </annotation>
        <annotation annotator="Mike Bada, University of Colorado Anschutz Medical Campus" id="CL_basic_2014_02_21_Instance_12437" type="identity">
            <class id="CL:0000542"/>
            <span end="22104" id="17244351-11314" start="22094">lymphocyte</span>
        </annotation>
        <annotation annotator="Mike Bada, University of Colorado Anschutz Medical Campus" id="CL_basic_2014_02_21_Instance_12445" type="identity">
            <class id="CL:0000542"/>
            <span end="22162" id="17244351-11316" start="22151">lymphocytes</span>
        </annotation>
        <annotation annotator="Mike Bada, University of Colorado Anschutz Medical Campus" id="CL_basic_2014_02_21_Instance_70274" type="identity">
            <class id="CL_UBERON_EXT:lymphocyte_or_lymphoid_progenitor_or_system_or_tissue"/>
            <span end="23617" id="17244351-11318" start="23609">lymphoid</span>
        </annotation>
        <annotation annotator="Mike Bada, University of Colorado Anschutz Medical Campus" id="CL_basic_2014_02_21_Instance_11533" type="identity">
            <class id="CL:0000815"/>
            <span end="23865" id="17244351-11302" start="23848">regulatory T cell</span>
        </annotation>
        <annotation annotator="Mike Bada, University of Colorado Anschutz Medical Campus" id="CL_basic_2014_02_21_Instance_10079" type="identity">
            <class id="CL_GO_EXT:cell"/>
            <span end="29236" id="17244351-11300" start="29232">cell</span>
        </annotation>
        <graph-space id="Old Knowtator Relations"/>
    </document>
</knowtator-project>
